Topsis_Aditya_102053005/topsis.py
Topsis_Aditya_102053005-0.16.dist-info/License.txt
Topsis_Aditya_102053005-0.16.dist-info/METADATA
Topsis_Aditya_102053005-0.16.dist-info/WHEEL
Topsis_Aditya_102053005-0.16.dist-info/entry_points.txt
Topsis_Aditya_102053005-0.16.dist-info/top_level.txt
Topsis_Aditya_102053005-0.16.dist-info/RECORD
