Metadata-Version: 2.1
Name: Topsis-Aditya-102053005
Version: 0.16
Summary: This is a package for implementing Topsis
Home-page: https://github.com/Adityakalhan/102053005-Aditya-Topsis
Author: Aditya Kalhan
License: MIT
Classifier: License :: OSI Approved :: MIT License
Classifier: Programming Language :: Python :: 3.6
Classifier: Programming Language :: Python :: 3.7
Classifier: Programming Language :: Python :: 3.8
License-File: License.txt
Requires-Dist: pandas
